LICENSE
README.md
setup.py
Corpus/AbstractCorpus.c
Corpus/AbstractCorpus.pxd
Corpus/AbstractCorpus.pyx
Corpus/Corpus.c
Corpus/Corpus.pxd
Corpus/Corpus.pyx
Corpus/CorpusStream.c
Corpus/CorpusStream.pxd
Corpus/CorpusStream.pyx
Corpus/EnglishSplitter.c
Corpus/EnglishSplitter.pxd
Corpus/EnglishSplitter.pyx
Corpus/FileDescription.c
Corpus/FileDescription.pxd
Corpus/FileDescription.pyx
Corpus/LanguageChecker.c
Corpus/LanguageChecker.pxd
Corpus/LanguageChecker.pyx
Corpus/Paragraph.c
Corpus/Paragraph.pxd
Corpus/Paragraph.pyx
Corpus/Sentence.c
Corpus/Sentence.pxd
Corpus/Sentence.pyx
Corpus/SentenceSplitter.c
Corpus/SentenceSplitter.pxd
Corpus/SentenceSplitter.pyx
Corpus/TurkishChecker.c
Corpus/TurkishChecker.pyx
Corpus/TurkishSplitter.c
Corpus/TurkishSplitter.pxd
Corpus/TurkishSplitter.pyx
Corpus/WordFormat.py
Corpus/__init__.py
NlpToolkit_Corpus_Cy.egg-info/PKG-INFO
NlpToolkit_Corpus_Cy.egg-info/SOURCES.txt
NlpToolkit_Corpus_Cy.egg-info/dependency_links.txt
NlpToolkit_Corpus_Cy.egg-info/requires.txt
NlpToolkit_Corpus_Cy.egg-info/top_level.txt
nlptoolkit_corpus_cy.egg-info/PKG-INFO
nlptoolkit_corpus_cy.egg-info/SOURCES.txt
nlptoolkit_corpus_cy.egg-info/dependency_links.txt
nlptoolkit_corpus_cy.egg-info/requires.txt
nlptoolkit_corpus_cy.egg-info/top_level.txt