Metadata-Version: 2.4
Name: nlptoolkit-corpus-cy
Version: 1.0.23
Summary: Corpus library
Home-page: https://github.com/StarlangSoftware/Corpus-Cy
Author: olcaytaner
Author-email: olcay.yildiz@ozyegin.edu.tr
License-File: LICENSE
Requires-Dist: NlpToolkit-Dictionary-Cy
Requires-Dist: NlpToolkit-DataStructure-Cy
Dynamic: author
Dynamic: author-email
Dynamic: description
Dynamic: description-content-type
Dynamic: home-page
Dynamic: license-file
Dynamic: requires-dist
Dynamic: summary
